AUTHORS
CHANGELOG
INSTALL
LICENSE
MANIFEST.in
README
setup.py
django_iso3166.egg-info/PKG-INFO
django_iso3166.egg-info/SOURCES.txt
django_iso3166.egg-info/dependency_links.txt
django_iso3166.egg-info/not-zip-safe
django_iso3166.egg-info/requires.txt
django_iso3166.egg-info/top_level.txt
iso3166/__init__.py
iso3166/admin.py
iso3166/fields.py
iso3166/models.py
iso3166/testsettings.py
iso3166/fixtures/initial_fixtures.json
iso3166/forms/__init__.py
iso3166/forms/fields.py
iso3166/management/__init__.py
iso3166/management/commands/__init__.py
iso3166/management/commands/updateISO3166.py
iso3166/tests/__init__.py