Metadata-Version: 1.0
Name: django-iso3166
Version: 10.1
Summary: This is a application for Django projects providing list of world countries based on ISO3166.
Home-page: https://trac.co-capacity.biz/trac/cocap/wiki/django-ISO3166
Author: Co-Capacity
Author-email: django-iso3166@co-capacity.org
License: UNKNOWN
Download-URL: http://files.co-capacity.org/iso3166/releases/django-iso3166-10.1.tar.gz
Platform: UNKNOWN
Classifier: Development Status :: 4 - Beta
Classifier: Environment :: Web Environment
Classifier: Framework :: Django
Classifier: Intended Audience :: Developers
Classifier: License :: OSI Approved :: BSD License
Classifier: Operating System :: OS Independent
Classifier: Programming Language :: Python
Classifier: Topic :: Internet :: WWW/HTTP
